Metadata-Version: 2.1
Name: wealthwatchdog
Version: 0.1
Summary: A personal finance calculator library
Home-page: https://github.com/RaviTejaJp/WealthWatchDog.git
Author: Jammulapati Ravi Teja
Author-email: ravitejajammulapti@gmail.com
Classifier: Programming Language :: Python :: 3
Classifier: License :: OSI Approved :: MIT License
Classifier: Operating System :: OS Independent
License-File: License
